LICENSE.txt
MANIFEST.in
requirements.txt
setup.cfg
setup.py
checkio_cli/__init__.py
checkio_cli/cli.py
checkio_cli/folder.py
checkio_cli/getters.py
checkio_cli/initial.py
checkio_cli/testing.py
checkio_cli.egg-info/PKG-INFO
checkio_cli.egg-info/SOURCES.txt
checkio_cli.egg-info/dependency_links.txt
checkio_cli.egg-info/entry_points.txt
checkio_cli.egg-info/requires.txt
checkio_cli.egg-info/top_level.txt
checkio_cli/config/__init__.py
checkio_cli/config/exceptions.py
checkio_cli/config/initial_config.py
checkio_cli/config/settings.py
checkio_cli/config/tools.py
checkio_cli/interfaces/__init__.py
checkio_cli/interfaces/ifile.py
checkio_cli/interfaces/ifolder.py
checkio_cli/interfaces/igit.py