Metadata-Version: 1.1
Name: checkio-cli
Version: 0.0.20
Summary: CheckiO common line interface for run and debug mission
Home-page: https://github.com/CheckiO/checkio-cli
Author: CheckiO
Author-email: igor@checkio.org
License: UNKNOWN
Download-URL: https://github.com/CheckiO/checkio-cli/tarball/0.0.20
Platform: UNKNOWN
